{
  "phase": 33,
  "domain": "Chaos & Fractals",
  "title": "🪞 Ego Diffraction Fields",
  "emoji": "🪞",
  "name": "Ego Diffraction Fields",
  "what_it_is": "Fractal-optic zones that split ego into multiple angular components—each facet acting independently, creating diffraction-induced identity fragments.",
  "how_to_use": [
    "her ego hit the field—shattered into colors of self",
    "he argues with himself—and all selves are present"
  ],
  "good_for": [
    "Psychedelic breakdowns",
    "identity loss or reformation",
    "altered consciousness scenes"
  ],
  "visual_keywords": [
    "Prismatic egos",
    "angular self-beams",
    "fractured personality rays",
    "internal conflict shards"
  ],
  "animation_behavior": "Self refracts into multiples, each moving differently, light beams pulse in sync with inner emotion ---",
  "id": "chaos_p33_01"
}